MANIFEST.in
README.txt
setup.py
docs/HISTORY.txt
docs/INSTALL.txt
docs/LICENSE.GPL
docs/LICENSE.txt
ngi/__init__.py
ngi.site.notification.egg-info/PKG-INFO
ngi.site.notification.egg-info/SOURCES.txt
ngi.site.notification.egg-info/dependency_links.txt
ngi.site.notification.egg-info/entry_points.txt
ngi.site.notification.egg-info/namespace_packages.txt
ngi.site.notification.egg-info/not-zip-safe
ngi.site.notification.egg-info/requires.txt
ngi.site.notification.egg-info/top_level.txt
ngi/site/__init__.py
ngi/site/notification/__init__.py
ngi/site/notification/configure.zcml
ngi/site/notification/events.py
ngi/site/notification/interfaces.py
ngi/site/notification/tests.py
ngi/site/notification/version.txt
ngi/site/notification/controlpanel/__init__.py
ngi/site/notification/controlpanel/configure.zcml
ngi/site/notification/controlpanel/cp.py
ngi/site/notification/profiles/default/controlpanel.xml
ngi/site/notification/profiles/default/metadata.xml
ngi/site/notification/profiles/default/registry.xml