Metadata-Version: 1.0
Name: ngi.site.notification
Version: 1.0
Summary: Changing a Plone content  into a designated state, tweets in Twitter.
Home-page: http://ngi644.net
Author: Takashi NAGAI
Author-email: nagai@ngi644.net
License: GPL
Keywords: Plone
Platform: UNKNOWN
Classifier: Framework :: Plone
Classifier: Programming Language :: Python
